ptydriver/__init__.py
ptydriver/keys.py
ptydriver/process.py
ptydriver/py.typed
ptydriver-0.2.0.dist-info/METADATA
ptydriver-0.2.0.dist-info/WHEEL
ptydriver-0.2.0.dist-info/licenses/LICENSE
ptydriver-0.2.0.dist-info/RECORD
