Metadata-Version: 2.4
Name: ptydriver
Version: 0.2.0
Summary: Programmatically drive interactive terminal applications via PTY
Project-URL: Homepage, https://github.com/brandon-fryslie/ptydriver
Project-URL: Repository, https://github.com/brandon-fryslie/ptydriver
Author: Brandon Fryslie
License-Expression: MIT
License-File: LICENSE
Keywords: automation,cli,interactive,pexpect,pty,terminal,tty,tui
Classifier: Development Status :: 4 - Beta
Classifier: Environment :: Console
Classifier: Intended Audience :: Developers
Classifier: License :: OSI Approved :: MIT License
Classifier: Operating System :: MacOS
Classifier: Operating System :: POSIX :: Linux
Classifier: Programming Language :: Python :: 3
Classifier: Programming Language :: Python :: 3.8
Classifier: Programming Language :: Python :: 3.9
Classifier: Programming Language :: Python :: 3.10
Classifier: Programming Language :: Python :: 3.11
Classifier: Programming Language :: Python :: 3.12
Classifier: Topic :: Software Development :: Libraries
Classifier: Topic :: System :: Shells
Classifier: Topic :: Terminals
Requires-Python: >=3.8
Requires-Dist: ptyprocess>=0.7.0
Requires-Dist: pyte>=0.8.0
Provides-Extra: dev
Requires-Dist: build>=1.0.0; extra == 'dev'
Requires-Dist: commitizen>=3.0.0; extra == 'dev'
Requires-Dist: mypy>=1.0.0; extra == 'dev'
Requires-Dist: pre-commit>=3.0.0; extra == 'dev'
Requires-Dist: pytest-timeout>=2.0.0; extra == 'dev'
Requires-Dist: pytest>=7.0.0; extra == 'dev'
Requires-Dist: ruff>=0.1.0; extra == 'dev'
Requires-Dist: twine>=4.0.0; extra == 'dev'
